{
 "cells": [
  {
   "cell_type": "code",
   "execution_count": 1,
   "metadata": {},
   "outputs": [],
   "source": [
    "def f1(a):\n",
    "    print(a)\n",
    "    print(b)"
   ]
  },
  {
   "cell_type": "code",
   "execution_count": 2,
   "metadata": {},
   "outputs": [
    {
     "name": "stdout",
     "output_type": "stream",
     "text": [
      "3\n"
     ]
    },
    {
     "ename": "NameError",
     "evalue": "name 'b' is not defined",
     "output_type": "error",
     "traceback": [
      "\u001b[0;31m---------------------------------------------------------------------------\u001b[0m",
      "\u001b[0;31mNameError\u001b[0m                                 Traceback (most recent call last)",
      "\u001b[1;32m/Users/bytedance/Documents/project/python/PythonCollections/util/get_bytecode.ipynb Cell 2\u001b[0m in \u001b[0;36m<cell line: 1>\u001b[0;34m()\u001b[0m\n\u001b[0;32m----> <a href='vscode-notebook-cell:/Users/bytedance/Documents/project/python/PythonCollections/util/get_bytecode.ipynb#W1sZmlsZQ%3D%3D?line=0'>1</a>\u001b[0m f1(\u001b[39m3\u001b[39;49m)\n",
      "\u001b[1;32m/Users/bytedance/Documents/project/python/PythonCollections/util/get_bytecode.ipynb Cell 2\u001b[0m in \u001b[0;36mf1\u001b[0;34m(a)\u001b[0m\n\u001b[1;32m      <a href='vscode-notebook-cell:/Users/bytedance/Documents/project/python/PythonCollections/util/get_bytecode.ipynb#W1sZmlsZQ%3D%3D?line=0'>1</a>\u001b[0m \u001b[39mdef\u001b[39;00m \u001b[39mf1\u001b[39m(a):\n\u001b[1;32m      <a href='vscode-notebook-cell:/Users/bytedance/Documents/project/python/PythonCollections/util/get_bytecode.ipynb#W1sZmlsZQ%3D%3D?line=1'>2</a>\u001b[0m     \u001b[39mprint\u001b[39m(a)\n\u001b[0;32m----> <a href='vscode-notebook-cell:/Users/bytedance/Documents/project/python/PythonCollections/util/get_bytecode.ipynb#W1sZmlsZQ%3D%3D?line=2'>3</a>\u001b[0m     \u001b[39mprint\u001b[39m(b)\n",
      "\u001b[0;31mNameError\u001b[0m: name 'b' is not defined"
     ]
    }
   ],
   "source": [
    "f1(3)"
   ]
  },
  {
   "cell_type": "code",
   "execution_count": 3,
   "metadata": {},
   "outputs": [
    {
     "name": "stdout",
     "output_type": "stream",
     "text": [
      "  2           0 LOAD_GLOBAL              0 (print)\n",
      "              2 LOAD_FAST                0 (a)\n",
      "              4 CALL_FUNCTION            1\n",
      "              6 POP_TOP\n",
      "\n",
      "  3           8 LOAD_GLOBAL              0 (print)\n",
      "             10 LOAD_GLOBAL              1 (b)\n",
      "             12 CALL_FUNCTION            1\n",
      "             14 POP_TOP\n",
      "             16 LOAD_CONST               0 (None)\n",
      "             18 RETURN_VALUE\n"
     ]
    }
   ],
   "source": [
    "from dis import dis\n",
    "dis(f1)"
   ]
  },
  {
   "cell_type": "code",
   "execution_count": 4,
   "metadata": {},
   "outputs": [],
   "source": [
    "def f2(a):\n",
    "    print(a)\n",
    "    print(b)\n",
    "    b = 9"
   ]
  },
  {
   "cell_type": "code",
   "execution_count": 6,
   "metadata": {},
   "outputs": [
    {
     "name": "stdout",
     "output_type": "stream",
     "text": [
      "3\n"
     ]
    },
    {
     "ename": "UnboundLocalError",
     "evalue": "local variable 'b' referenced before assignment",
     "output_type": "error",
     "traceback": [
      "\u001b[0;31m---------------------------------------------------------------------------\u001b[0m",
      "\u001b[0;31mUnboundLocalError\u001b[0m                         Traceback (most recent call last)",
      "\u001b[1;32m/Users/bytedance/Documents/project/python/PythonCollections/util/get_bytecode.ipynb Cell 5\u001b[0m in \u001b[0;36m<cell line: 1>\u001b[0;34m()\u001b[0m\n\u001b[0;32m----> <a href='vscode-notebook-cell:/Users/bytedance/Documents/project/python/PythonCollections/util/get_bytecode.ipynb#W6sZmlsZQ%3D%3D?line=0'>1</a>\u001b[0m f2(\u001b[39m3\u001b[39;49m)\n",
      "\u001b[1;32m/Users/bytedance/Documents/project/python/PythonCollections/util/get_bytecode.ipynb Cell 5\u001b[0m in \u001b[0;36mf2\u001b[0;34m(a)\u001b[0m\n\u001b[1;32m      <a href='vscode-notebook-cell:/Users/bytedance/Documents/project/python/PythonCollections/util/get_bytecode.ipynb#W6sZmlsZQ%3D%3D?line=0'>1</a>\u001b[0m \u001b[39mdef\u001b[39;00m \u001b[39mf2\u001b[39m(a):\n\u001b[1;32m      <a href='vscode-notebook-cell:/Users/bytedance/Documents/project/python/PythonCollections/util/get_bytecode.ipynb#W6sZmlsZQ%3D%3D?line=1'>2</a>\u001b[0m     \u001b[39mprint\u001b[39m(a)\n\u001b[0;32m----> <a href='vscode-notebook-cell:/Users/bytedance/Documents/project/python/PythonCollections/util/get_bytecode.ipynb#W6sZmlsZQ%3D%3D?line=2'>3</a>\u001b[0m     \u001b[39mprint\u001b[39m(b)\n\u001b[1;32m      <a href='vscode-notebook-cell:/Users/bytedance/Documents/project/python/PythonCollections/util/get_bytecode.ipynb#W6sZmlsZQ%3D%3D?line=3'>4</a>\u001b[0m     b \u001b[39m=\u001b[39m \u001b[39m9\u001b[39m\n",
      "\u001b[0;31mUnboundLocalError\u001b[0m: local variable 'b' referenced before assignment"
     ]
    }
   ],
   "source": [
    "f2(3)"
   ]
  },
  {
   "cell_type": "code",
   "execution_count": 7,
   "metadata": {},
   "outputs": [
    {
     "name": "stdout",
     "output_type": "stream",
     "text": [
      "  2           0 LOAD_GLOBAL              0 (print)\n",
      "              2 LOAD_FAST                0 (a)\n",
      "              4 CALL_FUNCTION            1\n",
      "              6 POP_TOP\n",
      "\n",
      "  3           8 LOAD_GLOBAL              0 (print)\n",
      "             10 LOAD_FAST                1 (b)\n",
      "             12 CALL_FUNCTION            1\n",
      "             14 POP_TOP\n",
      "\n",
      "  4          16 LOAD_CONST               1 (9)\n",
      "             18 STORE_FAST               1 (b)\n",
      "             20 LOAD_CONST               0 (None)\n",
      "             22 RETURN_VALUE\n"
     ]
    }
   ],
   "source": [
    "dis(f2)"
   ]
  },
  {
   "cell_type": "markdown",
   "metadata": {},
   "source": [
    "闭包的概念：\\\n",
    "函数是不是匿名的没有关系，关键是它能访问定义体之外定义的非全局变量。"
   ]
  },
  {
   "cell_type": "markdown",
   "metadata": {},
   "source": []
  }
 ],
 "metadata": {
  "kernelspec": {
   "display_name": "Python 3.10.6 64-bit",
   "language": "python",
   "name": "python3"
  },
  "language_info": {
   "codemirror_mode": {
    "name": "ipython",
    "version": 3
   },
   "file_extension": ".py",
   "mimetype": "text/x-python",
   "name": "python",
   "nbconvert_exporter": "python",
   "pygments_lexer": "ipython3",
   "version": "3.10.6"
  },
  "orig_nbformat": 4,
  "vscode": {
   "interpreter": {
    "hash": "aee8b7b246df8f9039afb4144a1f6fd8d2ca17a180786b69acc140d282b71a49"
   }
  }
 },
 "nbformat": 4,
 "nbformat_minor": 2
}
